langchain_google_vertexai_yd/__init__.py
langchain_google_vertexai_yd/_anthropic_parsers.py
langchain_google_vertexai_yd/_anthropic_utils.py
langchain_google_vertexai_yd/_base.py
langchain_google_vertexai_yd/_enums.py
langchain_google_vertexai_yd/_image_utils.py
langchain_google_vertexai_yd/_retry.py
langchain_google_vertexai_yd/_utils.py
langchain_google_vertexai_yd/callbacks.py
langchain_google_vertexai_yd/chains.py
langchain_google_vertexai_yd/chat_models.py
langchain_google_vertexai_yd/embeddings.py
langchain_google_vertexai_yd/evaluators/__init__.py
langchain_google_vertexai_yd/evaluators/_core.py
langchain_google_vertexai_yd/evaluators/evaluation.py
langchain_google_vertexai_yd/functions_utils.py
langchain_google_vertexai_yd/gemma.py
langchain_google_vertexai_yd/llms.py
langchain_google_vertexai_yd/model_garden.py
langchain_google_vertexai_yd/model_garden_maas/__init__.py
langchain_google_vertexai_yd/model_garden_maas/_base.py
langchain_google_vertexai_yd/model_garden_maas/llama.py
langchain_google_vertexai_yd/model_garden_maas/mistral.py
langchain_google_vertexai_yd/py.typed
langchain_google_vertexai_yd/utils.py
langchain_google_vertexai_yd/vectorstores/__init__.py
langchain_google_vertexai_yd/vectorstores/_sdk_manager.py
langchain_google_vertexai_yd/vectorstores/_searcher.py
langchain_google_vertexai_yd/vectorstores/_utils.py
langchain_google_vertexai_yd/vectorstores/document_storage.py
langchain_google_vertexai_yd/vectorstores/vectorstores.py
langchain_google_vertexai_yd/vision_models.py
langchain_google_vertexai_yd-2.0.21rc1.dist-info/LICENSE
langchain_google_vertexai_yd-2.0.21rc1.dist-info/METADATA
langchain_google_vertexai_yd-2.0.21rc1.dist-info/WHEEL
langchain_google_vertexai_yd-2.0.21rc1.dist-info/RECORD
