Metadata-Version: 2.3
Name: langchain-google-vertexai_yd
Version: 2.0.21rc1
Summary: An integration package connecting Google VertexAI and LangChain
License: MIT
Requires-Python: >=3.9,<4.0
Classifier: License :: OSI Approved :: MIT License
Classifier: Programming Language :: Python :: 3
Classifier: Programming Language :: Python :: 3.9
Classifier: Programming Language :: Python :: 3.10
Classifier: Programming Language :: Python :: 3.11
Classifier: Programming Language :: Python :: 3.12
Classifier: Programming Language :: Python :: 3.13
Provides-Extra: anthropic
Provides-Extra: mistral
Requires-Dist: anthropic[vertexai] (>=0.35.0,<1) ; extra == "anthropic"
Requires-Dist: bottleneck (>=1.4.2,<2.0.0)
Requires-Dist: google-cloud-aiplatform (>=1.91.0,<2.0.0)
Requires-Dist: google-cloud-storage (>=2.18.0,<3.0.0)
Requires-Dist: httpx (>=0.28.0,<0.29.0)
Requires-Dist: httpx-sse (>=0.4.0,<0.5.0)
Requires-Dist: langchain-core (>=0.3.55,<0.4)
Requires-Dist: langchain-mistralai (>=0.2.0,<1) ; extra == "mistral"
Requires-Dist: numexpr (>=2.8.6,<3.0.0)
Requires-Dist: pyarrow (>=19.0.1,<20.0.0)
Requires-Dist: pydantic (>=2.9,<3.0)
Requires-Dist: validators (>=0.22.0,<1)
Project-URL: Repository, https://github.com/langchain-ai/langchain-google
Project-URL: Source Code, https://github.com/langchain-ai/langchain-google/tree/main/libs/vertexai
